ascend_variant_provider/__init__.py
ascend_variant_provider/detect_cann.py
ascend_variant_provider/plugin.py
ascend_variant_provider/pysmi.py
ascend_variant_provider-0.0.2.dist-info/entry_points.txt
ascend_variant_provider-0.0.2.dist-info/licenses/LICENSE
ascend_variant_provider-0.0.2.dist-info/WHEEL
ascend_variant_provider-0.0.2.dist-info/METADATA
ascend_variant_provider-0.0.2.dist-info/RECORD
