Metadata-Version: 2.4
Name: ascend-variant-provider
Version: 0.0.2
Summary: WheelNext Variant Provider for Ascend CANN"
Author: WheelNext Community
Maintainer-email: Zhihang Deng <zhihangdeng@link.cuhk.edu.com>
Requires-Python: >=3.9
License-File: LICENSE
Project-URL: Home, https://github.com/wheelnext/ascend-variant-provider/
